{"inputs":{"node_modules/react-refresh/cjs/react-refresh-runtime.development.js":{"bytes":20419,"imports":[],"format":"cjs"},"node_modules/react-refresh/runtime.js":{"bytes":222,"imports":[{"path":"node_modules/react-refresh/cjs/react-refresh-runtime.development.js","kind":"require-call","original":"./cjs/react-refresh-runtime.development.js"}],"format":"cjs"},"hmr-runtime:remix:hmr":{"bytes":1944,"imports":[{"path":"node_modules/react-refresh/runtime.js","kind":"import-statement","original":"D:/repositories/RSschool-react-7/node_modules/react-refresh/runtime.js"}],"format":"esm"},"node_modules/react/cjs/react.development.js":{"bytes":87593,"imports":[],"format":"cjs"},"node_modules/react/index.js":{"bytes":190,"imports":[{"path":"node_modules/react/cjs/react.development.js","kind":"require-call","original":"./cjs/react.development.js"}],"format":"cjs"},"node_modules/scheduler/cjs/scheduler.development.js":{"bytes":17497,"imports":[],"format":"cjs"},"node_modules/scheduler/index.js":{"bytes":198,"imports":[{"path":"node_modules/scheduler/cjs/scheduler.development.js","kind":"require-call","original":"./cjs/scheduler.development.js"}],"format":"cjs"},"node_modules/react-dom/cjs/react-dom.development.js":{"bytes":1029622,"imports":[{"path":"node_modules/react/index.js","kind":"require-call","original":"react"},{"path":"node_modules/scheduler/index.js","kind":"require-call","original":"scheduler"}],"format":"cjs"},"node_modules/react-dom/index.js":{"bytes":1363,"imports":[{"path":"node_modules/react-dom/cjs/react-dom.development.js","kind":"require-call","original":"./cjs/react-dom.development.js"}],"format":"cjs"},"node_modules/@remix-run/router/dist/router.js":{"bytes":193568,"imports":[],"format":"esm"},"node_modules/react-router/dist/index.js":{"bytes":58290,"imports":[{"path":"node_modules/react/index.js","kind":"import-statement","original":"react"},{"path":"node_modules/@remix-run/router/dist/router.js","kind":"import-statement","original":"@remix-run/router"},{"path":"node_modules/@remix-run/router/dist/router.js","kind":"import-statement","original":"@remix-run/router"}],"format":"esm"},"node_modules/react-router-dom/dist/index.js":{"bytes":56505,"imports":[{"path":"node_modules/react/index.js","kind":"import-statement","original":"react"},{"path":"node_modules/react-dom/index.js","kind":"import-statement","original":"react-dom"},{"path":"node_modules/react-router/dist/index.js","kind":"import-statement","original":"react-router"},{"path":"node_modules/react-router/dist/index.js","kind":"import-statement","original":"react-router"},{"path":"node_modules/@remix-run/router/dist/router.js","kind":"import-statement","original":"@remix-run/router"},{"path":"node_modules/@remix-run/router/dist/router.js","kind":"import-statement","original":"@remix-run/router"}],"format":"esm"},"node_modules/cookie/index.js":{"bytes":5281,"imports":[],"format":"cjs"},"node_modules/@remix-run/server-runtime/dist/esm/warnings.js":{"bytes":439,"imports":[],"format":"esm"},"node_modules/@remix-run/server-runtime/dist/esm/cookies.js":{"bytes":4989,"imports":[{"path":"node_modules/cookie/index.js","kind":"import-statement","original":"cookie"},{"path":"node_modules/@remix-run/server-runtime/dist/esm/warnings.js","kind":"import-statement","original":"./warnings.js"}],"format":"esm"},"node_modules/@web3-storage/multipart-parser/esm/src/utils.js":{"bytes":722,"imports":[],"format":"esm"},"node_modules/@web3-storage/multipart-parser/esm/src/search.js":{"bytes":6918,"imports":[{"path":"node_modules/@web3-storage/multipart-parser/esm/src/utils.js","kind":"import-statement","original":"./utils.js"}],"format":"esm"},"node_modules/@web3-storage/multipart-parser/esm/src/index.js":{"bytes":6352,"imports":[{"path":"node_modules/@web3-storage/multipart-parser/esm/src/search.js","kind":"import-statement","original":"./search.js"},{"path":"node_modules/@web3-storage/multipart-parser/esm/src/utils.js","kind":"import-statement","original":"./utils.js"}],"format":"esm"},"node_modules/@remix-run/server-runtime/dist/esm/formData.js":{"bytes":1713,"imports":[{"path":"node_modules/@web3-storage/multipart-parser/esm/src/index.js","kind":"import-statement","original":"@web3-storage/multipart-parser"}],"format":"esm"},"node_modules/@remix-run/server-runtime/dist/esm/mode.js":{"bytes":667,"imports":[],"format":"esm"},"node_modules/@remix-run/server-runtime/dist/esm/errors.js":{"bytes":4411,"imports":[{"path":"node_modules/@remix-run/router/dist/router.js","kind":"import-statement","original":"@remix-run/router"},{"path":"node_modules/@remix-run/server-runtime/dist/esm/mode.js","kind":"import-statement","original":"./mode.js"}],"format":"esm"},"node_modules/@remix-run/server-runtime/dist/esm/responses.js":{"bytes":4709,"imports":[{"path":"node_modules/@remix-run/router/dist/router.js","kind":"import-statement","original":"@remix-run/router"},{"path":"node_modules/@remix-run/server-runtime/dist/esm/errors.js","kind":"import-statement","original":"./errors.js"}],"format":"esm"},"node_modules/turbo-stream/dist/turbo-stream.mjs":{"bytes":16560,"imports":[],"format":"esm"},"node_modules/set-cookie-parser/lib/set-cookie.js":{"bytes":6732,"imports":[],"format":"cjs"},"node_modules/@remix-run/server-runtime/dist/esm/headers.js":{"bytes":3329,"imports":[{"path":"node_modules/set-cookie-parser/lib/set-cookie.js","kind":"import-statement","original":"set-cookie-parser"}],"format":"esm"},"node_modules/@remix-run/server-runtime/dist/esm/single-fetch.js":{"bytes":10565,"imports":[{"path":"node_modules/@remix-run/router/dist/router.js","kind":"import-statement","original":"@remix-run/router"},{"path":"node_modules/turbo-stream/dist/turbo-stream.mjs","kind":"import-statement","original":"turbo-stream"},{"path":"node_modules/@remix-run/server-runtime/dist/esm/errors.js","kind":"import-statement","original":"./errors.js"},{"path":"node_modules/@remix-run/server-runtime/dist/esm/headers.js","kind":"import-statement","original":"./headers.js"},{"path":"node_modules/@remix-run/server-runtime/dist/esm/mode.js","kind":"import-statement","original":"./mode.js"},{"path":"node_modules/@remix-run/server-runtime/dist/esm/responses.js","kind":"import-statement","original":"./responses.js"}],"format":"esm"},"node_modules/@remix-run/server-runtime/dist/esm/entry.js":{"bytes":452,"imports":[],"format":"esm"},"node_modules/@remix-run/server-runtime/dist/esm/invariant.js":{"bytes":547,"imports":[],"format":"esm"},"node_modules/@remix-run/server-runtime/dist/esm/routeMatching.js":{"bytes":581,"imports":[{"path":"node_modules/@remix-run/router/dist/router.js","kind":"import-statement","original":"@remix-run/router"}],"format":"esm"},"node_modules/@remix-run/server-runtime/dist/esm/data.js":{"bytes":3361,"imports":[{"path":"node_modules/@remix-run/server-runtime/dist/esm/responses.js","kind":"import-statement","original":"./responses.js"}],"format":"esm"},"node_modules/@remix-run/server-runtime/dist/esm/routes.js":{"bytes":2691,"imports":[{"path":"node_modules/@remix-run/server-runtime/dist/esm/data.js","kind":"import-statement","original":"./data.js"}],"format":"esm"},"node_modules/@remix-run/server-runtime/dist/esm/markup.js":{"bytes":896,"imports":[],"format":"esm"},"node_modules/@remix-run/server-runtime/dist/esm/serverHandoff.js":{"bytes":628,"imports":[{"path":"node_modules/@remix-run/server-runtime/dist/esm/markup.js","kind":"import-statement","original":"./markup.js"}],"format":"esm"},"node_modules/@remix-run/server-runtime/dist/esm/dev.js":{"bytes":1358,"imports":[],"format":"esm"},"node_modules/@remix-run/server-runtime/dist/esm/deprecations.js":{"bytes":778,"imports":[],"format":"esm"},"node_modules/@remix-run/server-runtime/dist/esm/server.js":{"bytes":19522,"imports":[{"path":"node_modules/@remix-run/router/dist/router.js","kind":"import-statement","original":"@remix-run/router"},{"path":"node_modules/@remix-run/server-runtime/dist/esm/entry.js","kind":"import-statement","original":"./entry.js"},{"path":"node_modules/@remix-run/server-runtime/dist/esm/errors.js","kind":"import-statement","original":"./errors.js"},{"path":"node_modules/@remix-run/server-runtime/dist/esm/headers.js","kind":"import-statement","original":"./headers.js"},{"path":"node_modules/@remix-run/server-runtime/dist/esm/invariant.js","kind":"import-statement","original":"./invariant.js"},{"path":"node_modules/@remix-run/server-runtime/dist/esm/mode.js","kind":"import-statement","original":"./mode.js"},{"path":"node_modules/@remix-run/server-runtime/dist/esm/routeMatching.js","kind":"import-statement","original":"./routeMatching.js"},{"path":"node_modules/@remix-run/server-runtime/dist/esm/routes.js","kind":"import-statement","original":"./routes.js"},{"path":"node_modules/@remix-run/server-runtime/dist/esm/responses.js","kind":"import-statement","original":"./responses.js"},{"path":"node_modules/@remix-run/server-runtime/dist/esm/serverHandoff.js","kind":"import-statement","original":"./serverHandoff.js"},{"path":"node_modules/@remix-run/server-runtime/dist/esm/dev.js","kind":"import-statement","original":"./dev.js"},{"path":"node_modules/@remix-run/server-runtime/dist/esm/single-fetch.js","kind":"import-statement","original":"./single-fetch.js"},{"path":"node_modules/@remix-run/server-runtime/dist/esm/deprecations.js","kind":"import-statement","original":"./deprecations.js"}],"format":"esm"},"node_modules/@remix-run/server-runtime/dist/esm/sessions.js":{"bytes":4710,"imports":[{"path":"node_modules/@remix-run/server-runtime/dist/esm/cookies.js","kind":"import-statement","original":"./cookies.js"},{"path":"node_modules/@remix-run/server-runtime/dist/esm/warnings.js","kind":"import-statement","original":"./warnings.js"}],"format":"esm"},"node_modules/@remix-run/server-runtime/dist/esm/sessions/cookieStorage.js":{"bytes":1838,"imports":[{"path":"node_modules/@remix-run/server-runtime/dist/esm/cookies.js","kind":"import-statement","original":"../cookies.js"},{"path":"node_modules/@remix-run/server-runtime/dist/esm/sessions.js","kind":"import-statement","original":"../sessions.js"}],"format":"esm"},"node_modules/@remix-run/server-runtime/dist/esm/sessions/memoryStorage.js":{"bytes":1441,"imports":[],"format":"esm"},"node_modules/@remix-run/server-runtime/dist/esm/upload/errors.js":{"bytes":488,"imports":[],"format":"esm"},"node_modules/@remix-run/server-runtime/dist/esm/upload/memoryUploadHandler.js":{"bytes":1061,"imports":[{"path":"node_modules/@remix-run/server-runtime/dist/esm/upload/errors.js","kind":"import-statement","original":"./errors.js"}],"format":"esm"},"node_modules/@remix-run/server-runtime/dist/esm/index.js":{"bytes":1316,"imports":[{"path":"node_modules/@remix-run/server-runtime/dist/esm/cookies.js","kind":"import-statement","original":"./cookies.js"},{"path":"node_modules/@remix-run/server-runtime/dist/esm/formData.js","kind":"import-statement","original":"./formData.js"},{"path":"node_modules/@remix-run/server-runtime/dist/esm/responses.js","kind":"import-statement","original":"./responses.js"},{"path":"node_modules/@remix-run/server-runtime/dist/esm/single-fetch.js","kind":"import-statement","original":"./single-fetch.js"},{"path":"node_modules/@remix-run/server-runtime/dist/esm/server.js","kind":"import-statement","original":"./server.js"},{"path":"node_modules/@remix-run/server-runtime/dist/esm/sessions.js","kind":"import-statement","original":"./sessions.js"},{"path":"node_modules/@remix-run/server-runtime/dist/esm/sessions/cookieStorage.js","kind":"import-statement","original":"./sessions/cookieStorage.js"},{"path":"node_modules/@remix-run/server-runtime/dist/esm/sessions/memoryStorage.js","kind":"import-statement","original":"./sessions/memoryStorage.js"},{"path":"node_modules/@remix-run/server-runtime/dist/esm/upload/memoryUploadHandler.js","kind":"import-statement","original":"./upload/memoryUploadHandler.js"},{"path":"node_modules/@remix-run/server-runtime/dist/esm/upload/errors.js","kind":"import-statement","original":"./upload/errors.js"},{"path":"node_modules/@remix-run/server-runtime/dist/esm/dev.js","kind":"import-statement","original":"./dev.js"}],"format":"esm"},"node_modules/@remix-run/react/dist/esm/_virtual/_rollupPluginBabelHelpers.js":{"bytes":662,"imports":[],"format":"esm"},"node_modules/@remix-run/react/dist/esm/invariant.js":{"bytes":409,"imports":[],"format":"esm"},"node_modules/@remix-run/react/dist/esm/routeModules.js":{"bytes":2905,"imports":[],"format":"esm"},"node_modules/@remix-run/react/dist/esm/links.js":{"bytes":9658,"imports":[{"path":"node_modules/react-router-dom/dist/index.js","kind":"import-statement","original":"react-router-dom"},{"path":"node_modules/@remix-run/react/dist/esm/routeModules.js","kind":"import-statement","original":"./routeModules.js"}],"format":"esm"},"node_modules/@remix-run/react/dist/esm/markup.js":{"bytes":962,"imports":[],"format":"esm"},"node_modules/@remix-run/react/dist/esm/data.js":{"bytes":10265,"imports":[{"path":"node_modules/@remix-run/router/dist/router.js","kind":"import-statement","original":"@remix-run/router"}],"format":"esm"},"node_modules/@remix-run/react/dist/esm/single-fetch.js":{"bytes":11327,"imports":[{"path":"node_modules/react/index.js","kind":"import-statement","original":"react"},{"path":"node_modules/@remix-run/router/dist/router.js","kind":"import-statement","original":"@remix-run/router"},{"path":"node_modules/@remix-run/server-runtime/dist/esm/index.js","kind":"import-statement","original":"@remix-run/server-runtime"},{"path":"node_modules/turbo-stream/dist/turbo-stream.mjs","kind":"import-statement","original":"turbo-stream"},{"path":"node_modules/@remix-run/react/dist/esm/data.js","kind":"import-statement","original":"./data.js"},{"path":"node_modules/@remix-run/react/dist/esm/markup.js","kind":"import-statement","original":"./markup.js"},{"path":"node_modules/@remix-run/react/dist/esm/invariant.js","kind":"import-statement","original":"./invariant.js"}],"format":"esm"},"node_modules/@remix-run/react/dist/esm/errorBoundaries.js":{"bytes":5612,"imports":[{"path":"node_modules/react/index.js","kind":"import-statement","original":"react"},{"path":"node_modules/react-router-dom/dist/index.js","kind":"import-statement","original":"react-router-dom"},{"path":"node_modules/@remix-run/react/dist/esm/components.js","kind":"import-statement","original":"./components.js"}],"format":"esm"},"node_modules/@remix-run/react/dist/esm/fallback.js":{"bytes":1202,"imports":[{"path":"node_modules/react/index.js","kind":"import-statement","original":"react"},{"path":"node_modules/@remix-run/react/dist/esm/errorBoundaries.js","kind":"import-statement","original":"./errorBoundaries.js"}],"format":"esm"},"node_modules/@remix-run/react/dist/esm/routes.js":{"bytes":17734,"imports":[{"path":"node_modules/react/index.js","kind":"import-statement","original":"react"},{"path":"node_modules/@remix-run/router/dist/router.js","kind":"import-statement","original":"@remix-run/router"},{"path":"node_modules/react-router-dom/dist/index.js","kind":"import-statement","original":"react-router-dom"},{"path":"node_modules/@remix-run/react/dist/esm/routeModules.js","kind":"import-statement","original":"./routeModules.js"},{"path":"node_modules/@remix-run/react/dist/esm/data.js","kind":"import-statement","original":"./data.js"},{"path":"node_modules/@remix-run/react/dist/esm/links.js","kind":"import-statement","original":"./links.js"},{"path":"node_modules/@remix-run/react/dist/esm/errorBoundaries.js","kind":"import-statement","original":"./errorBoundaries.js"},{"path":"node_modules/@remix-run/react/dist/esm/fallback.js","kind":"import-statement","original":"./fallback.js"},{"path":"node_modules/@remix-run/react/dist/esm/invariant.js","kind":"import-statement","original":"./invariant.js"}],"format":"esm"},"node_modules/@remix-run/react/dist/esm/fog-of-war.js":{"bytes":7761,"imports":[{"path":"node_modules/@remix-run/router/dist/router.js","kind":"import-statement","original":"@remix-run/router"},{"path":"node_modules/react/index.js","kind":"import-statement","original":"react"},{"path":"node_modules/@remix-run/react/dist/esm/routes.js","kind":"import-statement","original":"./routes.js"}],"format":"esm"},"node_modules/@remix-run/react/dist/esm/components.js":{"bytes":34517,"imports":[{"path":"node_modules/@remix-run/react/dist/esm/_virtual/_rollupPluginBabelHelpers.js","kind":"import-statement","original":"./_virtual/_rollupPluginBabelHelpers.js"},{"path":"node_modules/react/index.js","kind":"import-statement","original":"react"},{"path":"node_modules/react-router-dom/dist/index.js","kind":"import-statement","original":"react-router-dom"},{"path":"node_modules/@remix-run/react/dist/esm/invariant.js","kind":"import-statement","original":"./invariant.js"},{"path":"node_modules/@remix-run/react/dist/esm/links.js","kind":"import-statement","original":"./links.js"},{"path":"node_modules/@remix-run/react/dist/esm/markup.js","kind":"import-statement","original":"./markup.js"},{"path":"node_modules/@remix-run/react/dist/esm/single-fetch.js","kind":"import-statement","original":"./single-fetch.js"},{"path":"node_modules/@remix-run/react/dist/esm/fog-of-war.js","kind":"import-statement","original":"./fog-of-war.js"}],"format":"esm"},"node_modules/@remix-run/react/dist/esm/errors.js":{"bytes":1581,"imports":[{"path":"node_modules/@remix-run/router/dist/router.js","kind":"import-statement","original":"@remix-run/router"}],"format":"esm"},"node_modules/@remix-run/react/dist/esm/browser.js":{"bytes":15581,"imports":[{"path":"hmr-runtime:remix:hmr","kind":"import-statement","original":"remix:hmr"},{"path":"node_modules/@remix-run/router/dist/router.js","kind":"import-statement","original":"@remix-run/router"},{"path":"node_modules/react/index.js","kind":"import-statement","original":"react"},{"path":"node_modules/react-router/dist/index.js","kind":"import-statement","original":"react-router"},{"path":"node_modules/react-router-dom/dist/index.js","kind":"import-statement","original":"react-router-dom"},{"path":"node_modules/@remix-run/react/dist/esm/components.js","kind":"import-statement","original":"./components.js"},{"path":"node_modules/@remix-run/react/dist/esm/errorBoundaries.js","kind":"import-statement","original":"./errorBoundaries.js"},{"path":"node_modules/@remix-run/react/dist/esm/errors.js","kind":"import-statement","original":"./errors.js"},{"path":"node_modules/@remix-run/react/dist/esm/routes.js","kind":"import-statement","original":"./routes.js"},{"path":"node_modules/@remix-run/react/dist/esm/single-fetch.js","kind":"import-statement","original":"./single-fetch.js"},{"path":"node_modules/@remix-run/react/dist/esm/invariant.js","kind":"import-statement","original":"./invariant.js"},{"path":"node_modules/@remix-run/react/dist/esm/fog-of-war.js","kind":"import-statement","original":"./fog-of-war.js"}],"format":"esm"},"node_modules/@remix-run/react/dist/esm/scroll-restoration.js":{"bytes":2665,"imports":[{"path":"node_modules/@remix-run/react/dist/esm/_virtual/_rollupPluginBabelHelpers.js","kind":"import-statement","original":"./_virtual/_rollupPluginBabelHelpers.js"},{"path":"node_modules/react/index.js","kind":"import-statement","original":"react"},{"path":"node_modules/react-router-dom/dist/index.js","kind":"import-statement","original":"react-router-dom"},{"path":"node_modules/@remix-run/react/dist/esm/components.js","kind":"import-statement","original":"./components.js"}],"format":"esm"},"node_modules/react-router-dom/server.js":{"bytes":10633,"imports":[{"path":"node_modules/react/index.js","kind":"require-call","original":"react"},{"path":"node_modules/@remix-run/router/dist/router.js","kind":"require-call","original":"@remix-run/router"},{"path":"node_modules/react-router/dist/index.js","kind":"require-call","original":"react-router"},{"path":"node_modules/react-router-dom/dist/index.js","kind":"require-call","original":"react-router-dom"}],"format":"cjs"},"node_modules/@remix-run/react/dist/esm/server.js":{"bytes":3423,"imports":[{"path":"node_modules/react/index.js","kind":"import-statement","original":"react"},{"path":"node_modules/react-router-dom/server.js","kind":"import-statement","original":"react-router-dom/server"},{"path":"node_modules/@remix-run/react/dist/esm/components.js","kind":"import-statement","original":"./components.js"},{"path":"node_modules/@remix-run/react/dist/esm/errorBoundaries.js","kind":"import-statement","original":"./errorBoundaries.js"},{"path":"node_modules/@remix-run/react/dist/esm/routes.js","kind":"import-statement","original":"./routes.js"},{"path":"node_modules/@remix-run/react/dist/esm/single-fetch.js","kind":"import-statement","original":"./single-fetch.js"}],"format":"esm"},"node_modules/@remix-run/react/dist/esm/index.js":{"bytes":1503,"imports":[{"path":"node_modules/react-router-dom/dist/index.js","kind":"import-statement","original":"react-router-dom"},{"path":"node_modules/@remix-run/server-runtime/dist/esm/index.js","kind":"import-statement","original":"@remix-run/server-runtime"},{"path":"node_modules/@remix-run/react/dist/esm/browser.js","kind":"import-statement","original":"./browser.js"},{"path":"node_modules/@remix-run/react/dist/esm/components.js","kind":"import-statement","original":"./components.js"},{"path":"node_modules/@remix-run/react/dist/esm/scroll-restoration.js","kind":"import-statement","original":"./scroll-restoration.js"},{"path":"node_modules/@remix-run/react/dist/esm/server.js","kind":"import-statement","original":"./server.js"},{"path":"node_modules/@remix-run/react/dist/esm/single-fetch.js","kind":"import-statement","original":"./single-fetch.js"}],"format":"esm"},"node_modules/react-dom/client.js":{"bytes":619,"imports":[{"path":"node_modules/react-dom/index.js","kind":"require-call","original":"react-dom"}],"format":"cjs"},"node_modules/react/cjs/react-jsx-dev-runtime.development.js":{"bytes":42101,"imports":[{"path":"node_modules/react/index.js","kind":"require-call","original":"react"}],"format":"cjs"},"node_modules/react/jsx-dev-runtime.js":{"bytes":222,"imports":[{"path":"node_modules/react/cjs/react-jsx-dev-runtime.development.js","kind":"require-call","original":"./cjs/react-jsx-dev-runtime.development.js"}],"format":"cjs"},"app/entry.client.tsx":{"bytes":511,"imports":[{"path":"hmr-runtime:remix:hmr","kind":"import-statement","original":"remix:hmr"},{"path":"node_modules/@remix-run/react/dist/esm/index.js","kind":"import-statement","original":"@remix-run/react"},{"path":"node_modules/react/index.js","kind":"import-statement","original":"react"},{"path":"node_modules/react-dom/client.js","kind":"import-statement","original":"react-dom/client"},{"path":"node_modules/react/jsx-dev-runtime.js","kind":"import-statement","original":"react/jsx-dev-runtime"}],"format":"esm"},"node_modules/use-sync-external-store/cjs/use-sync-external-store-with-selector.development.js":{"bytes":5639,"imports":[{"path":"node_modules/react/index.js","kind":"require-call","original":"react"}],"format":"cjs"},"node_modules/use-sync-external-store/with-selector.js":{"bytes":254,"imports":[{"path":"node_modules/use-sync-external-store/cjs/use-sync-external-store-with-selector.development.js","kind":"require-call","original":"./cjs/use-sync-external-store-with-selector.development.js"}],"format":"cjs"},"node_modules/react-redux/dist/react-redux.mjs":{"bytes":37868,"imports":[{"path":"node_modules/react/index.js","kind":"import-statement","original":"react"},{"path":"node_modules/use-sync-external-store/with-selector.js","kind":"import-statement","original":"use-sync-external-store/with-selector.js"},{"path":"node_modules/react/index.js","kind":"import-statement","original":"react"}],"format":"esm"},"node_modules/redux/dist/redux.mjs":{"bytes":16765,"imports":[],"format":"esm"},"node_modules/immer/dist/immer.mjs":{"bytes":36195,"imports":[],"format":"esm"},"node_modules/reselect/dist/reselect.mjs":{"bytes":21982,"imports":[],"format":"esm"},"node_modules/redux-thunk/dist/redux-thunk.mjs":{"bytes":417,"imports":[],"format":"esm"},"node_modules/@reduxjs/toolkit/dist/redux-toolkit.modern.mjs":{"bytes":78283,"imports":[{"path":"node_modules/redux/dist/redux.mjs","kind":"import-statement","original":"redux"},{"path":"node_modules/immer/dist/immer.mjs","kind":"import-statement","original":"immer"},{"path":"node_modules/reselect/dist/reselect.mjs","kind":"import-statement","original":"reselect"},{"path":"node_modules/immer/dist/immer.mjs","kind":"import-statement","original":"immer"},{"path":"node_modules/reselect/dist/reselect.mjs","kind":"import-statement","original":"reselect"},{"path":"node_modules/redux/dist/redux.mjs","kind":"import-statement","original":"redux"},{"path":"node_modules/redux/dist/redux.mjs","kind":"import-statement","original":"redux"},{"path":"node_modules/redux-thunk/dist/redux-thunk.mjs","kind":"import-statement","original":"redux-thunk"},{"path":"node_modules/redux/dist/redux.mjs","kind":"import-statement","original":"redux"},{"path":"node_modules/immer/dist/immer.mjs","kind":"import-statement","original":"immer"},{"path":"node_modules/redux/dist/redux.mjs","kind":"import-statement","original":"redux"},{"path":"node_modules/immer/dist/immer.mjs","kind":"import-statement","original":"immer"},{"path":"node_modules/immer/dist/immer.mjs","kind":"import-statement","original":"immer"},{"path":"node_modules/immer/dist/immer.mjs","kind":"import-statement","original":"immer"},{"path":"node_modules/redux/dist/redux.mjs","kind":"import-statement","original":"redux"},{"path":"node_modules/redux/dist/redux.mjs","kind":"import-statement","original":"redux"},{"path":"node_modules/redux/dist/redux.mjs","kind":"import-statement","original":"redux"}],"format":"esm"},"app/store/selectedPeopleSlice.ts":{"bytes":1520,"imports":[{"path":"hmr-runtime:remix:hmr","kind":"import-statement","original":"remix:hmr"},{"path":"@components/card/ICardProps","kind":"import-statement","external":true},{"path":"node_modules/@reduxjs/toolkit/dist/redux-toolkit.modern.mjs","kind":"import-statement","original":"@reduxjs/toolkit"},{"path":"./store","kind":"import-statement","external":true}],"format":"esm"},"app/store/activeCardSlice.ts":{"bytes":791,"imports":[{"path":"hmr-runtime:remix:hmr","kind":"import-statement","original":"remix:hmr"},{"path":"node_modules/@reduxjs/toolkit/dist/redux-toolkit.modern.mjs","kind":"import-statement","original":"@reduxjs/toolkit"}],"format":"esm"},"node_modules/@reduxjs/toolkit/dist/query/rtk-query.modern.mjs":{"bytes":79113,"imports":[{"path":"node_modules/@reduxjs/toolkit/dist/redux-toolkit.modern.mjs","kind":"import-statement","original":"@reduxjs/toolkit"},{"path":"node_modules/immer/dist/immer.mjs","kind":"import-statement","original":"immer"},{"path":"node_modules/@reduxjs/toolkit/dist/redux-toolkit.modern.mjs","kind":"import-statement","original":"@reduxjs/toolkit"},{"path":"node_modules/immer/dist/immer.mjs","kind":"import-statement","original":"immer"},{"path":"node_modules/immer/dist/immer.mjs","kind":"import-statement","original":"immer"},{"path":"node_modules/@reduxjs/toolkit/dist/redux-toolkit.modern.mjs","kind":"import-statement","original":"@reduxjs/toolkit"},{"path":"node_modules/reselect/dist/reselect.mjs","kind":"import-statement","original":"reselect"},{"path":"node_modules/@reduxjs/toolkit/dist/redux-toolkit.modern.mjs","kind":"import-statement","original":"@reduxjs/toolkit"},{"path":"node_modules/immer/dist/immer.mjs","kind":"import-statement","original":"immer"},{"path":"node_modules/immer/dist/immer.mjs","kind":"import-statement","original":"immer"}],"format":"esm"},"node_modules/@reduxjs/toolkit/dist/query/react/rtk-query-react.modern.mjs":{"bytes":21723,"imports":[{"path":"node_modules/@reduxjs/toolkit/dist/query/rtk-query.modern.mjs","kind":"import-statement","original":"@reduxjs/toolkit/query"},{"path":"node_modules/@reduxjs/toolkit/dist/redux-toolkit.modern.mjs","kind":"import-statement","original":"@reduxjs/toolkit"},{"path":"node_modules/react-redux/dist/react-redux.mjs","kind":"import-statement","original":"react-redux"},{"path":"node_modules/reselect/dist/reselect.mjs","kind":"import-statement","original":"reselect"},{"path":"node_modules/@reduxjs/toolkit/dist/redux-toolkit.modern.mjs","kind":"import-statement","original":"@reduxjs/toolkit"},{"path":"node_modules/@reduxjs/toolkit/dist/redux-toolkit.modern.mjs","kind":"import-statement","original":"@reduxjs/toolkit"},{"path":"node_modules/@reduxjs/toolkit/dist/query/rtk-query.modern.mjs","kind":"import-statement","original":"@reduxjs/toolkit/query"},{"path":"node_modules/react/index.js","kind":"import-statement","original":"react"},{"path":"node_modules/react-redux/dist/react-redux.mjs","kind":"import-statement","original":"react-redux"},{"path":"node_modules/react/index.js","kind":"import-statement","original":"react"},{"path":"node_modules/react/index.js","kind":"import-statement","original":"react"},{"path":"node_modules/react-redux/dist/react-redux.mjs","kind":"import-statement","original":"react-redux"},{"path":"node_modules/@reduxjs/toolkit/dist/query/rtk-query.modern.mjs","kind":"import-statement","original":"@reduxjs/toolkit/query"},{"path":"node_modules/@reduxjs/toolkit/dist/redux-toolkit.modern.mjs","kind":"import-statement","original":"@reduxjs/toolkit"},{"path":"node_modules/react/index.js","kind":"import-statement","original":"react"},{"path":"node_modules/react/index.js","kind":"import-statement","original":"react"},{"path":"node_modules/react/index.js","kind":"import-statement","original":"react"},{"path":"node_modules/react-redux/dist/react-redux.mjs","kind":"import-statement","original":"react-redux"},{"path":"node_modules/@reduxjs/toolkit/dist/query/rtk-query.modern.mjs","kind":"import-statement","original":"@reduxjs/toolkit/query"}],"format":"esm"},"app-next/api/hello.ts":{"bytes":1207,"imports":[{"path":"hmr-runtime:remix:hmr","kind":"import-statement","original":"remix:hmr"},{"path":"node_modules/@reduxjs/toolkit/dist/query/react/rtk-query-react.modern.mjs","kind":"import-statement","original":"@reduxjs/toolkit/query/react"},{"path":"~/components/card/ICardProps","kind":"import-statement","external":true}],"format":"esm"},"app/store/store.ts":{"bytes":822,"imports":[{"path":"hmr-runtime:remix:hmr","kind":"import-statement","original":"remix:hmr"},{"path":"node_modules/@reduxjs/toolkit/dist/redux-toolkit.modern.mjs","kind":"import-statement","original":"@reduxjs/toolkit"},{"path":"app/store/selectedPeopleSlice.ts","kind":"import-statement","original":"./selectedPeopleSlice"},{"path":"app/store/activeCardSlice.ts","kind":"import-statement","original":"./activeCardSlice"},{"path":"app-next/api/hello.ts","kind":"import-statement","original":"../../app-next/api/hello"}],"format":"esm"},"css-bundle-plugin-ns:@remix-run/css-bundle":{"bytes":39,"imports":[],"format":"esm"},"app/index.css":{"bytes":9088,"imports":[]},"app/hooks/ThemeContext.tsx":{"bytes":1468,"imports":[{"path":"hmr-runtime:remix:hmr","kind":"import-statement","original":"remix:hmr"},{"path":"node_modules/react/index.js","kind":"import-statement","original":"react"},{"path":"node_modules/react/jsx-dev-runtime.js","kind":"import-statement","original":"react/jsx-dev-runtime"}],"format":"esm"},"app/root.tsx":{"bytes":2021,"imports":[{"path":"hmr-runtime:remix:hmr","kind":"import-statement","original":"remix:hmr"},{"path":"node_modules/@remix-run/react/dist/esm/index.js","kind":"import-statement","original":"@remix-run/react"},{"path":"node_modules/react-redux/dist/react-redux.mjs","kind":"import-statement","original":"react-redux"},{"path":"app/store/store.ts","kind":"import-statement","original":"./store/store"},{"path":"css-bundle-plugin-ns:@remix-run/css-bundle","kind":"import-statement","original":"@remix-run/css-bundle"},{"path":"app/index.css","kind":"import-statement","original":"./index.css"},{"path":"app/hooks/ThemeContext.tsx","kind":"import-statement","original":"./hooks/ThemeContext"},{"path":"node_modules/react/jsx-dev-runtime.js","kind":"import-statement","original":"react/jsx-dev-runtime"}],"format":"esm"},"browser-route-module:root.tsx?browser":{"bytes":50,"imports":[{"path":"app/root.tsx","kind":"import-statement","original":"./root.tsx"}],"format":"esm"},"app/components/button/Button.tsx":{"bytes":1409,"imports":[{"path":"hmr-runtime:remix:hmr","kind":"import-statement","original":"remix:hmr"},{"path":"react","kind":"import-statement","external":true},{"path":"node_modules/react/jsx-dev-runtime.js","kind":"import-statement","original":"react/jsx-dev-runtime"}],"format":"esm"},"app/components/card/detailedCard/DetailedCard.tsx":{"bytes":1733,"imports":[{"path":"hmr-runtime:remix:hmr","kind":"import-statement","original":"remix:hmr"},{"path":"node_modules/react/jsx-dev-runtime.js","kind":"import-statement","original":"react/jsx-dev-runtime"}],"format":"esm"},"app-next/details/[personId]/page.tsx":{"bytes":1931,"imports":[{"path":"hmr-runtime:remix:hmr","kind":"import-statement","original":"remix:hmr"},{"path":"react","kind":"import-statement","external":true},{"path":"app-next/api/hello.ts","kind":"import-statement","original":"../../api/hello"},{"path":"app/components/button/Button.tsx","kind":"import-statement","original":"~/components/button/Button"},{"path":"app/components/card/detailedCard/DetailedCard.tsx","kind":"import-statement","original":"~/components/card/detailedCard/DetailedCard"},{"path":"node_modules/react/jsx-dev-runtime.js","kind":"import-statement","original":"react/jsx-dev-runtime"}],"format":"esm"},"app/hooks/useTheme.ts":{"bytes":565,"imports":[{"path":"hmr-runtime:remix:hmr","kind":"import-statement","original":"remix:hmr"},{"path":"node_modules/react/index.js","kind":"import-statement","original":"react"},{"path":"app/hooks/ThemeContext.tsx","kind":"import-statement","original":"./ThemeContext"}],"format":"esm"},"app/components/checkbox/Checkbox.tsx":{"bytes":1599,"imports":[{"path":"hmr-runtime:remix:hmr","kind":"import-statement","original":"remix:hmr"},{"path":"app/hooks/useTheme.ts","kind":"import-statement","original":"../../hooks/useTheme"},{"path":"react","kind":"import-statement","external":true},{"path":"node_modules/react/jsx-dev-runtime.js","kind":"import-statement","original":"react/jsx-dev-runtime"}],"format":"esm"},"app/components/card/baseCard/Card.tsx":{"bytes":2101,"imports":[{"path":"hmr-runtime:remix:hmr","kind":"import-statement","original":"remix:hmr"},{"path":"app/store/selectedPeopleSlice.ts","kind":"import-statement","original":"../../../store/selectedPeopleSlice"},{"path":"node_modules/react-redux/dist/react-redux.mjs","kind":"import-statement","original":"react-redux"},{"path":"app/components/checkbox/Checkbox.tsx","kind":"import-statement","original":"../../checkbox/Checkbox"},{"path":"node_modules/react/jsx-dev-runtime.js","kind":"import-statement","original":"react/jsx-dev-runtime"}],"format":"esm"},"app/components/cardList/CardList.tsx":{"bytes":1851,"imports":[{"path":"hmr-runtime:remix:hmr","kind":"import-statement","original":"remix:hmr"},{"path":"app/store/activeCardSlice.ts","kind":"import-statement","original":"../../store/activeCardSlice"},{"path":"app/components/card/baseCard/Card.tsx","kind":"import-statement","original":"../card/baseCard/Card"},{"path":"node_modules/react-redux/dist/react-redux.mjs","kind":"import-statement","original":"react-redux"},{"path":"node_modules/react/jsx-dev-runtime.js","kind":"import-statement","original":"react/jsx-dev-runtime"}],"format":"esm"},"app/components/floatingPanel/FloatingPanel.tsx":{"bytes":3236,"imports":[{"path":"hmr-runtime:remix:hmr","kind":"import-statement","original":"remix:hmr"},{"path":"node_modules/react/index.js","kind":"import-statement","original":"react"},{"path":"node_modules/react-redux/dist/react-redux.mjs","kind":"import-statement","original":"react-redux"},{"path":"app/hooks/useTheme.ts","kind":"import-statement","original":"../../hooks/useTheme"},{"path":"app/store/selectedPeopleSlice.ts","kind":"import-statement","original":"../../store/selectedPeopleSlice"},{"path":"app/components/button/Button.tsx","kind":"import-statement","original":"../button/Button"},{"path":"node_modules/react/jsx-dev-runtime.js","kind":"import-statement","original":"react/jsx-dev-runtime"}],"format":"esm"},"app/components/Input/SearchInput/SearchInput.tsx":{"bytes":1296,"imports":[{"path":"hmr-runtime:remix:hmr","kind":"import-statement","original":"remix:hmr"},{"path":"node_modules/react/jsx-dev-runtime.js","kind":"import-statement","original":"react/jsx-dev-runtime"}],"format":"esm"},"app/components/pagination/Pagination.tsx":{"bytes":1795,"imports":[{"path":"hmr-runtime:remix:hmr","kind":"import-statement","original":"remix:hmr"},{"path":"app/components/button/Button.tsx","kind":"import-statement","original":"../button/Button"},{"path":"node_modules/react/jsx-dev-runtime.js","kind":"import-statement","original":"react/jsx-dev-runtime"}],"format":"esm"},"app/hooks/hooks.tsx":{"bytes":900,"imports":[{"path":"hmr-runtime:remix:hmr","kind":"import-statement","original":"remix:hmr"},{"path":"node_modules/react/index.js","kind":"import-statement","original":"react"}],"format":"esm"},"app-next/page.tsx":{"bytes":5019,"imports":[{"path":"hmr-runtime:remix:hmr","kind":"import-statement","original":"remix:hmr"},{"path":"node_modules/react/index.js","kind":"import-statement","original":"react"},{"path":"app-next/api/hello.ts","kind":"import-statement","original":"./api/hello"},{"path":"app-next/details/[personId]/page.tsx","kind":"import-statement","original":"./details/[personId]/page"},{"path":"app/components/button/Button.tsx","kind":"import-statement","original":"~/components/button/Button"},{"path":"app/components/cardList/CardList.tsx","kind":"import-statement","original":"~/components/cardList/CardList"},{"path":"app/components/floatingPanel/FloatingPanel.tsx","kind":"import-statement","original":"~/components/floatingPanel/FloatingPanel"},{"path":"app/components/Input/SearchInput/SearchInput.tsx","kind":"import-statement","original":"~/components/Input/SearchInput/SearchInput"},{"path":"app/components/pagination/Pagination.tsx","kind":"import-statement","original":"~/components/pagination/Pagination"},{"path":"app/hooks/hooks.tsx","kind":"import-statement","original":"~/hooks/hooks"},{"path":"app/hooks/useTheme.ts","kind":"import-statement","original":"~/hooks/useTheme"},{"path":"node_modules/@remix-run/react/dist/esm/index.js","kind":"import-statement","original":"@remix-run/react"},{"path":"node_modules/react/jsx-dev-runtime.js","kind":"import-statement","original":"react/jsx-dev-runtime"}],"format":"esm"},"app/routes/_index.tsx":{"bytes":288,"imports":[{"path":"hmr-runtime:remix:hmr","kind":"import-statement","original":"remix:hmr"},{"path":"app-next/page.tsx","kind":"import-statement","original":"../../app-next/page"}],"format":"esm"},"browser-route-module:routes/_index.tsx?browser":{"bytes":46,"imports":[{"path":"app/routes/_index.tsx","kind":"import-statement","original":"./routes/_index.tsx"}],"format":"esm"},"app/routes/$.tsx":{"bytes":282,"imports":[{"path":"hmr-runtime:remix:hmr","kind":"import-statement","original":"remix:hmr"},{"path":"app-next/page.tsx","kind":"import-statement","original":"../../app-next/page"}],"format":"esm"},"browser-route-module:routes/$.tsx?browser":{"bytes":41,"imports":[{"path":"app/routes/$.tsx","kind":"import-statement","original":"./routes/$.tsx"}],"format":"esm"},"node_modules/react/cjs/react-jsx-runtime.development.js":{"bytes":42700,"imports":[{"path":"node_modules/react/index.js","kind":"require-call","original":"react"}],"format":"cjs"},"node_modules/react/jsx-runtime.js":{"bytes":214,"imports":[{"path":"node_modules/react/cjs/react-jsx-runtime.development.js","kind":"require-call","original":"./cjs/react-jsx-runtime.development.js"}],"format":"cjs"},"node_modules/@remix-run/dev/dist/config/defaults/entry.dev.ts":{"bytes":289,"imports":[{"path":"node_modules/react/index.js","kind":"dynamic-import","original":"react"},{"path":"node_modules/react/jsx-dev-runtime.js","kind":"dynamic-import","original":"react/jsx-dev-runtime"},{"path":"node_modules/react/jsx-runtime.js","kind":"dynamic-import","original":"react/jsx-runtime"},{"path":"node_modules/react-dom/index.js","kind":"dynamic-import","original":"react-dom"},{"path":"node_modules/react-dom/client.js","kind":"dynamic-import","original":"react-dom/client"},{"path":"node_modules/react-refresh/runtime.js","kind":"dynamic-import","original":"react-refresh/runtime"},{"path":"node_modules/@remix-run/react/dist/esm/index.js","kind":"dynamic-import","original":"@remix-run/react"},{"path":"hmr-runtime:remix:hmr","kind":"dynamic-import","original":"remix:hmr"}],"format":"esm"}},"outputs":{"public/build/_shared/react-dom-BNZYXLBA.js.map":{"imports":[],"exports":[],"inputs":{},"bytes":93},"public/build/_shared/react-dom-BNZYXLBA.js":{"imports":[{"path":"public/build/_shared/chunk-U4FRFQSK.js","kind":"import-statement"},{"path":"public/build/_shared/chunk-7M6SC7J5.js","kind":"import-statement"},{"path":"public/build/_shared/chunk-PNG5AS42.js","kind":"import-statement"}],"exports":["default"],"entryPoint":"node_modules/react-dom/index.js","inputs":{},"bytes":256},"public/build/_shared/esm-Z34KSYM4.js.map":{"imports":[],"exports":[],"inputs":{},"bytes":93},"public/build/_shared/esm-Z34KSYM4.js":{"imports":[{"path":"public/build/_shared/chunk-PVNSLVPX.js","kind":"import-statement"},{"path":"public/build/_shared/chunk-U4FRFQSK.js","kind":"import-statement"},{"path":"public/build/_shared/chunk-FJ44GY64.js","kind":"import-statement"},{"path":"public/build/_shared/chunk-UWV35TSL.js","kind":"import-statement"},{"path":"public/build/_shared/chunk-7M6SC7J5.js","kind":"import-statement"},{"path":"public/build/_shared/chunk-PNG5AS42.js","kind":"import-statement"}],"exports":["Await","Form","Link","Links","LiveReload","Meta","NavLink","Navigate","NavigationType","Outlet","PrefetchPageLinks","RemixBrowser","RemixServer","Route","Routes","Scripts","ScrollRestoration","UNSAFE_RemixContext","createPath","createRoutesFromChildren","createRoutesFromElements","createSearchParams","defer","generatePath","isRouteErrorResponse","json","matchPath","matchRoutes","parsePath","redirect","redirectDocument","renderMatches","replace","resolvePath","unstable_data","unstable_defineClientAction","unstable_defineClientLoader","unstable_usePrompt","unstable_useViewTransitionState","useActionData","useAsyncError","useAsyncValue","useBeforeUnload","useBlocker","useFetcher","useFetchers","useFormAction","useHref","useInRouterContext","useLinkClickHandler","useLoaderData","useLocation","useMatch","useMatches","useNavigate","useNavigation","useNavigationType","useOutlet","useOutletContext","useParams","useResolvedPath","useRevalidator","useRouteError","useRouteLoaderData","useRoutes","useSearchParams","useSubmit"],"entryPoint":"node_modules/@remix-run/react/dist/esm/index.js","inputs":{},"bytes":2586},"public/build/_shared/client-5SMAFQUD.js.map":{"imports":[],"exports":[],"inputs":{},"bytes":93},"public/build/_shared/client-5SMAFQUD.js":{"imports":[{"path":"public/build/_shared/chunk-O4BRYNJ4.js","kind":"import-statement"},{"path":"public/build/_shared/chunk-U4FRFQSK.js","kind":"import-statement"},{"path":"public/build/_shared/chunk-7M6SC7J5.js","kind":"import-statement"},{"path":"public/build/_shared/chunk-PNG5AS42.js","kind":"import-statement"}],"exports":["default"],"entryPoint":"node_modules/react-dom/client.js","inputs":{},"bytes":290},"public/build/_shared/jsx-dev-runtime-AMSG5B5Y.js.map":{"imports":[],"exports":[],"inputs":{},"bytes":93},"public/build/_shared/jsx-dev-runtime-AMSG5B5Y.js":{"imports":[{"path":"public/build/_shared/chunk-XGOTYLZ5.js","kind":"import-statement"},{"path":"public/build/_shared/chunk-7M6SC7J5.js","kind":"import-statement"},{"path":"public/build/_shared/chunk-PNG5AS42.js","kind":"import-statement"}],"exports":["default"],"entryPoint":"node_modules/react/jsx-dev-runtime.js","inputs":{},"bytes":274},"public/build/_shared/jsx-runtime-O5SBAOHY.js.map":{"imports":[],"exports":[],"inputs":{},"bytes":61943},"public/build/_shared/jsx-runtime-O5SBAOHY.js":{"imports":[{"path":"public/build/_shared/chunk-7M6SC7J5.js","kind":"import-statement"},{"path":"public/build/_shared/chunk-PNG5AS42.js","kind":"import-statement"}],"exports":["default"],"entryPoint":"node_modules/react/jsx-runtime.js","inputs":{"node_modules/react/cjs/react-jsx-runtime.development.js":{"bytesInOutput":36439},"node_modules/react/jsx-runtime.js":{"bytesInOutput":233}},"bytes":37350},"public/build/entry.client-V3O6XNFN.js.map":{"imports":[],"exports":[],"inputs":{},"bytes":970},"public/build/entry.client-V3O6XNFN.js":{"imports":[{"path":"public/build/_shared/chunk-O4BRYNJ4.js","kind":"import-statement"},{"path":"public/build/_shared/chunk-PVNSLVPX.js","kind":"import-statement"},{"path":"public/build/_shared/chunk-U4FRFQSK.js","kind":"import-statement"},{"path":"public/build/_shared/chunk-XGOTYLZ5.js","kind":"import-statement"},{"path":"public/build/_shared/chunk-FJ44GY64.js","kind":"import-statement"},{"path":"public/build/_shared/chunk-UWV35TSL.js","kind":"import-statement"},{"path":"public/build/_shared/chunk-7M6SC7J5.js","kind":"import-statement"},{"path":"public/build/_shared/chunk-PNG5AS42.js","kind":"import-statement"}],"exports":[],"entryPoint":"app/entry.client.tsx","inputs":{"app/entry.client.tsx":{"bytesInOutput":830}},"bytes":1413},"public/build/_shared/chunk-O4BRYNJ4.js.map":{"imports":[],"exports":[],"inputs":{},"bytes":1228},"public/build/_shared/chunk-O4BRYNJ4.js":{"imports":[{"path":"public/build/_shared/chunk-U4FRFQSK.js","kind":"import-statement"},{"path":"public/build/_shared/chunk-PNG5AS42.js","kind":"import-statement"}],"exports":["require_client"],"inputs":{"node_modules/react-dom/client.js":{"bytesInOutput":760}},"bytes":1022},"public/build/_assets/index-QFEZ24QT.css":{"imports":[],"exports":[],"inputs":{"app/index.css":{"bytesInOutput":9088}},"bytes":9088},"public/build/root-X4J3XYRO.js.map":{"imports":[],"exports":[],"inputs":{},"bytes":4930},"public/build/root-X4J3XYRO.js":{"imports":[{"path":"public/build/_shared/chunk-DOFVYQPE.js","kind":"import-statement"},{"path":"public/build/_shared/chunk-PVNSLVPX.js","kind":"import-statement"},{"path":"public/build/_shared/chunk-U4FRFQSK.js","kind":"import-statement"},{"path":"public/build/_shared/chunk-XGOTYLZ5.js","kind":"import-statement"},{"path":"public/build/_shared/chunk-FJ44GY64.js","kind":"import-statement"},{"path":"public/build/_shared/chunk-UWV35TSL.js","kind":"import-statement"},{"path":"public/build/_shared/chunk-7M6SC7J5.js","kind":"import-statement"},{"path":"public/build/_shared/chunk-PNG5AS42.js","kind":"import-statement"},{"path":"public/build/_assets/index-QFEZ24QT.css","kind":"file-loader"}],"exports":["default","links","meta"],"entryPoint":"browser-route-module:root.tsx?browser","inputs":{"app/store/store.ts":{"bytesInOutput":431},"css-bundle-plugin-ns:@remix-run/css-bundle":{"bytesInOutput":28},"app/index.css":{"bytesInOutput":55},"app/root.tsx":{"bytesInOutput":3605},"browser-route-module:root.tsx?browser":{"bytesInOutput":0}},"bytes":4955},"public/build/routes/_index-7WS4M4R3.js.map":{"imports":[],"exports":[],"inputs":{},"bytes":535},"public/build/routes/_index-7WS4M4R3.js":{"imports":[{"path":"public/build/_shared/chunk-32E3ZG7O.js","kind":"import-statement"},{"path":"public/build/_shared/chunk-DOFVYQPE.js","kind":"import-statement"},{"path":"public/build/_shared/chunk-PVNSLVPX.js","kind":"import-statement"},{"path":"public/build/_shared/chunk-U4FRFQSK.js","kind":"import-statement"},{"path":"public/build/_shared/chunk-XGOTYLZ5.js","kind":"import-statement"},{"path":"public/build/_shared/chunk-FJ44GY64.js","kind":"import-statement"},{"path":"public/build/_shared/chunk-UWV35TSL.js","kind":"import-statement"},{"path":"public/build/_shared/chunk-7M6SC7J5.js","kind":"import-statement"},{"path":"public/build/_shared/chunk-PNG5AS42.js","kind":"import-statement"}],"exports":["default"],"entryPoint":"browser-route-module:routes/_index.tsx?browser","inputs":{"app/routes/_index.tsx":{"bytesInOutput":172},"browser-route-module:routes/_index.tsx?browser":{"bytesInOutput":0}},"bytes":733},"public/build/routes/$-5BOJVWTE.js.map":{"imports":[],"exports":[],"inputs":{},"bytes":524},"public/build/routes/$-5BOJVWTE.js":{"imports":[{"path":"public/build/_shared/chunk-32E3ZG7O.js","kind":"import-statement"},{"path":"public/build/_shared/chunk-DOFVYQPE.js","kind":"import-statement"},{"path":"public/build/_shared/chunk-PVNSLVPX.js","kind":"import-statement"},{"path":"public/build/_shared/chunk-U4FRFQSK.js","kind":"import-statement"},{"path":"public/build/_shared/chunk-XGOTYLZ5.js","kind":"import-statement"},{"path":"public/build/_shared/chunk-FJ44GY64.js","kind":"import-statement"},{"path":"public/build/_shared/chunk-UWV35TSL.js","kind":"import-statement"},{"path":"public/build/_shared/chunk-7M6SC7J5.js","kind":"import-statement"},{"path":"public/build/_shared/chunk-PNG5AS42.js","kind":"import-statement"}],"exports":["default"],"entryPoint":"browser-route-module:routes/$.tsx?browser","inputs":{"app/routes/$.tsx":{"bytesInOutput":166},"browser-route-module:routes/$.tsx?browser":{"bytesInOutput":0}},"bytes":717},"public/build/_shared/chunk-32E3ZG7O.js.map":{"imports":[],"exports":[],"inputs":{},"bytes":40366},"public/build/_shared/chunk-32E3ZG7O.js":{"imports":[{"path":"public/build/_shared/chunk-DOFVYQPE.js","kind":"import-statement"},{"path":"public/build/_shared/chunk-PVNSLVPX.js","kind":"import-statement"},{"path":"public/build/_shared/chunk-XGOTYLZ5.js","kind":"import-statement"},{"path":"public/build/_shared/chunk-FJ44GY64.js","kind":"import-statement"},{"path":"public/build/_shared/chunk-7M6SC7J5.js","kind":"import-statement"},{"path":"public/build/_shared/chunk-PNG5AS42.js","kind":"import-statement"}],"exports":["page_default"],"inputs":{"app-next/page.tsx":{"bytesInOutput":8148},"app/components/button/Button.tsx":{"bytesInOutput":1916},"app/components/card/detailedCard/DetailedCard.tsx":{"bytesInOutput":4281},"app-next/details/[personId]/page.tsx":{"bytesInOutput":3246},"app/hooks/useTheme.ts":{"bytesInOutput":417},"app/components/checkbox/Checkbox.tsx":{"bytesInOutput":2068},"app/components/card/baseCard/Card.tsx":{"bytesInOutput":2888},"app/components/cardList/CardList.tsx":{"bytesInOutput":2041},"app/components/floatingPanel/FloatingPanel.tsx":{"bytesInOutput":4033},"app/components/Input/SearchInput/SearchInput.tsx":{"bytesInOutput":1849},"app/components/pagination/Pagination.tsx":{"bytesInOutput":2557},"app/hooks/hooks.tsx":{"bytesInOutput":831}},"bytes":35450},"public/build/_shared/chunk-DOFVYQPE.js.map":{"imports":[],"exports":[],"inputs":{},"bytes":903119},"public/build/_shared/chunk-DOFVYQPE.js":{"imports":[{"path":"public/build/_shared/chunk-XGOTYLZ5.js","kind":"import-statement"},{"path":"public/build/_shared/chunk-FJ44GY64.js","kind":"import-statement"},{"path":"public/build/_shared/chunk-7M6SC7J5.js","kind":"import-statement"},{"path":"public/build/_shared/chunk-PNG5AS42.js","kind":"import-statement"}],"exports":["Provider_default","ThemeContext","ThemeProvider","activeCardSlice_default","api","clearSelection","configureStore","getSelectedPeopleUrls","selectedPeopleSlice_default","setActiveCard","togglePersonSelection","useDispatch","useGetPeopleQuery","useGetPersonByIdQuery","useSelector"],"inputs":{"node_modules/use-sync-external-store/cjs/use-sync-external-store-with-selector.development.js":{"bytesInOutput":4014},"node_modules/use-sync-external-store/with-selector.js":{"bytesInOutput":293},"node_modules/react-redux/dist/react-redux.mjs":{"bytesInOutput":13018},"node_modules/redux/dist/redux.mjs":{"bytesInOutput":14248},"node_modules/@reduxjs/toolkit/dist/redux-toolkit.modern.mjs":{"bytesInOutput":42838},"node_modules/immer/dist/immer.mjs":{"bytesInOutput":27439},"node_modules/reselect/dist/reselect.mjs":{"bytesInOutput":10857},"node_modules/redux-thunk/dist/redux-thunk.mjs":{"bytesInOutput":360},"node_modules/@reduxjs/toolkit/dist/query/rtk-query.modern.mjs":{"bytesInOutput":72896},"node_modules/@reduxjs/toolkit/dist/query/react/rtk-query-react.modern.mjs":{"bytesInOutput":19411},"app-next/api/hello.ts":{"bytesInOutput":660},"app/hooks/ThemeContext.tsx":{"bytesInOutput":1626},"app/store/selectedPeopleSlice.ts":{"bytesInOutput":1081},"app/store/activeCardSlice.ts":{"bytesInOutput":529}},"bytes":211044},"public/build/_shared/chunk-PVNSLVPX.js.map":{"imports":[],"exports":[],"inputs":{},"bytes":822132},"public/build/_shared/chunk-PVNSLVPX.js":{"imports":[{"path":"public/build/_shared/chunk-U4FRFQSK.js","kind":"import-statement"},{"path":"public/build/_shared/chunk-FJ44GY64.js","kind":"import-statement"},{"path":"public/build/_shared/chunk-7M6SC7J5.js","kind":"import-statement"},{"path":"public/build/_shared/chunk-PNG5AS42.js","kind":"import-statement"}],"exports":["Action","Await","Form","Link","Links","LiveReload","Meta","NavLink","Navigate","Outlet","PrefetchPageLinks","RemixBrowser","RemixContext","RemixServer","Route","Routes","Scripts","ScrollRestoration","createPath","createRoutesFromChildren","createSearchParams","data","defer","defineClientAction","defineClientLoader","generatePath","isRouteErrorResponse","json","matchPath","matchRoutes","parsePath","redirect","redirectDocument","renderMatches","replace","resolvePath","useActionData","useAsyncError","useAsyncValue","useBeforeUnload","useBlocker","useFetcher","useFetchers","useFormAction","useHref","useInRouterContext","useLinkClickHandler","useLoaderData","useLocation","useMatch","useMatches","useNavigate","useNavigation","useNavigationType","useOutlet","useOutletContext","useParams","usePrompt","useResolvedPath","useRevalidator","useRouteError","useRouteLoaderData","useRoutes","useSearchParams","useSubmit","useViewTransitionState"],"inputs":{"node_modules/@remix-run/router/dist/router.js":{"bytesInOutput":142836},"node_modules/react-router/dist/index.js":{"bytesInOutput":42610},"node_modules/react-router-dom/dist/index.js":{"bytesInOutput":44113},"node_modules/react-router-dom/server.js":{"bytesInOutput":10663},"node_modules/@remix-run/react/dist/esm/index.js":{"bytesInOutput":14},"node_modules/@remix-run/server-runtime/dist/esm/responses.js":{"bytesInOutput":381},"node_modules/@remix-run/server-runtime/dist/esm/index.js":{"bytesInOutput":0},"node_modules/@remix-run/server-runtime/dist/esm/single-fetch.js":{"bytesInOutput":138},"node_modules/turbo-stream/dist/turbo-stream.mjs":{"bytesInOutput":7489},"node_modules/@remix-run/react/dist/esm/browser.js":{"bytesInOutput":9721},"node_modules/@remix-run/react/dist/esm/_virtual/_rollupPluginBabelHelpers.js":{"bytesInOutput":404},"node_modules/@remix-run/react/dist/esm/components.js":{"bytesInOutput":28131},"node_modules/@remix-run/react/dist/esm/invariant.js":{"bytesInOutput":149},"node_modules/@remix-run/react/dist/esm/links.js":{"bytesInOutput":7628},"node_modules/@remix-run/react/dist/esm/routeModules.js":{"bytesInOutput":658},"node_modules/@remix-run/react/dist/esm/markup.js":{"bytesInOutput":328},"node_modules/@remix-run/react/dist/esm/single-fetch.js":{"bytesInOutput":7942},"node_modules/@remix-run/react/dist/esm/data.js":{"bytesInOutput":7360},"node_modules/@remix-run/react/dist/esm/fog-of-war.js":{"bytesInOutput":6164},"node_modules/@remix-run/react/dist/esm/routes.js":{"bytesInOutput":14666},"node_modules/@remix-run/react/dist/esm/errorBoundaries.js":{"bytesInOutput":3394},"node_modules/@remix-run/react/dist/esm/fallback.js":{"bytesInOutput":646},"node_modules/@remix-run/react/dist/esm/errors.js":{"bytesInOutput":962},"node_modules/@remix-run/react/dist/esm/scroll-restoration.js":{"bytesInOutput":1553},"node_modules/@remix-run/react/dist/esm/server.js":{"bytesInOutput":2146}},"bytes":350172},"public/build/_shared/chunk-U4FRFQSK.js.map":{"imports":[],"exports":[],"inputs":{},"bytes":1492664},"public/build/_shared/chunk-U4FRFQSK.js":{"imports":[{"path":"public/build/_shared/chunk-7M6SC7J5.js","kind":"import-statement"},{"path":"public/build/_shared/chunk-PNG5AS42.js","kind":"import-statement"}],"exports":["require_react_dom"],"inputs":{"node_modules/scheduler/cjs/scheduler.development.js":{"bytesInOutput":16890},"node_modules/scheduler/index.js":{"bytesInOutput":239},"node_modules/react-dom/cjs/react-dom.development.js":{"bytesInOutput":910075},"node_modules/react-dom/index.js":{"bytesInOutput":239}},"bytes":928925},"public/build/_shared/chunk-XGOTYLZ5.js.map":{"imports":[],"exports":[],"inputs":{},"bytes":61116},"public/build/_shared/chunk-XGOTYLZ5.js":{"imports":[{"path":"public/build/_shared/chunk-7M6SC7J5.js","kind":"import-statement"},{"path":"public/build/_shared/chunk-PNG5AS42.js","kind":"import-statement"}],"exports":["require_jsx_dev_runtime"],"inputs":{"node_modules/react/cjs/react-jsx-dev-runtime.development.js":{"bytesInOutput":36064},"node_modules/react/jsx-dev-runtime.js":{"bytesInOutput":245}},"bytes":36998},"public/build/__remix_entry_dev-GZSAOUFB.js.map":{"imports":[],"exports":[],"inputs":{},"bytes":652},"public/build/__remix_entry_dev-GZSAOUFB.js":{"imports":[{"path":"public/build/_shared/chunk-PNG5AS42.js","kind":"import-statement"},{"path":"public/build/_shared/react-EAI2LDIX.js","kind":"dynamic-import"},{"path":"public/build/_shared/jsx-dev-runtime-AMSG5B5Y.js","kind":"dynamic-import"},{"path":"public/build/_shared/jsx-runtime-O5SBAOHY.js","kind":"dynamic-import"},{"path":"public/build/_shared/react-dom-BNZYXLBA.js","kind":"dynamic-import"},{"path":"public/build/_shared/client-5SMAFQUD.js","kind":"dynamic-import"},{"path":"public/build/_shared/runtime-GC7QIU56.js","kind":"dynamic-import"},{"path":"public/build/_shared/esm-Z34KSYM4.js","kind":"dynamic-import"},{"path":"public/build/_shared/remix_hmr-EOMDDF4B.js","kind":"dynamic-import"}],"exports":["default"],"entryPoint":"node_modules/@remix-run/dev/dist/config/defaults/entry.dev.ts","inputs":{"node_modules/@remix-run/dev/dist/config/defaults/entry.dev.ts":{"bytesInOutput":428}},"bytes":642},"public/build/_shared/runtime-GC7QIU56.js.map":{"imports":[],"exports":[],"inputs":{},"bytes":93},"public/build/_shared/runtime-GC7QIU56.js":{"imports":[{"path":"public/build/_shared/chunk-UWV35TSL.js","kind":"import-statement"},{"path":"public/build/_shared/chunk-PNG5AS42.js","kind":"import-statement"}],"exports":["default"],"entryPoint":"node_modules/react-refresh/runtime.js","inputs":{},"bytes":207},"public/build/_shared/remix_hmr-EOMDDF4B.js.map":{"imports":[],"exports":[],"inputs":{},"bytes":93},"public/build/_shared/remix_hmr-EOMDDF4B.js":{"imports":[{"path":"public/build/_shared/chunk-FJ44GY64.js","kind":"import-statement"},{"path":"public/build/_shared/chunk-UWV35TSL.js","kind":"import-statement"},{"path":"public/build/_shared/chunk-PNG5AS42.js","kind":"import-statement"}],"exports":["createHotContext"],"entryPoint":"hmr-runtime:remix:hmr","inputs":{},"bytes":250},"public/build/_shared/chunk-FJ44GY64.js.map":{"imports":[],"exports":[],"inputs":{},"bytes":3313},"public/build/_shared/chunk-FJ44GY64.js":{"imports":[{"path":"public/build/_shared/chunk-UWV35TSL.js","kind":"import-statement"},{"path":"public/build/_shared/chunk-PNG5AS42.js","kind":"import-statement"}],"exports":["createHotContext"],"inputs":{"hmr-runtime:remix:hmr":{"bytesInOutput":1648}},"bytes":1896},"public/build/_shared/chunk-UWV35TSL.js.map":{"imports":[],"exports":[],"inputs":{},"bytes":30368},"public/build/_shared/chunk-UWV35TSL.js":{"imports":[{"path":"public/build/_shared/chunk-PNG5AS42.js","kind":"import-statement"}],"exports":["require_runtime"],"inputs":{"node_modules/react-refresh/cjs/react-refresh-runtime.development.js":{"bytesInOutput":17196},"node_modules/react-refresh/runtime.js":{"bytesInOutput":237}},"bytes":18062},"public/build/_shared/react-EAI2LDIX.js.map":{"imports":[],"exports":[],"inputs":{},"bytes":93},"public/build/_shared/react-EAI2LDIX.js":{"imports":[{"path":"public/build/_shared/chunk-7M6SC7J5.js","kind":"import-statement"},{"path":"public/build/_shared/chunk-PNG5AS42.js","kind":"import-statement"}],"exports":["default"],"entryPoint":"node_modules/react/index.js","inputs":{},"bytes":201},"public/build/_shared/chunk-7M6SC7J5.js.map":{"imports":[],"exports":[],"inputs":{},"bytes":125635},"public/build/_shared/chunk-7M6SC7J5.js":{"imports":[{"path":"public/build/_shared/chunk-PNG5AS42.js","kind":"import-statement"}],"exports":["require_react"],"inputs":{"node_modules/react/cjs/react.development.js":{"bytesInOutput":77050},"node_modules/react/index.js":{"bytesInOutput":209}},"bytes":77812},"public/build/_shared/chunk-PNG5AS42.js.map":{"imports":[],"exports":[],"inputs":{},"bytes":93},"public/build/_shared/chunk-PNG5AS42.js":{"imports":[],"exports":["__commonJS","__esm","__export","__toCommonJS","__toESM"],"inputs":{},"bytes":1791}}}